histdata_downloader/__init__.py
histdata_downloader/cli.py
histdata_downloader/histdata_downloader.py
histdata_downloader/logger.py
histdata_downloader/tui.py
histdata_downloader-0.5.1.dist-info/AUTHORS.rst
histdata_downloader-0.5.1.dist-info/LICENSE
histdata_downloader-0.5.1.dist-info/METADATA
histdata_downloader-0.5.1.dist-info/WHEEL
histdata_downloader-0.5.1.dist-info/entry_points.txt
histdata_downloader-0.5.1.dist-info/top_level.txt
histdata_downloader-0.5.1.dist-info/RECORD
