Metadata-Version: 2.1
Name: histdata-downloader
Version: 0.5.1
Summary: Simple script to download forex historical data from 'www.histdata.com'
Home-page: https://github.com/tgrandjean/histdata-downloader
Author: Thibault Grandjean
Author-email: thibault.grandjean@protonmail.ch
License: MIT license
Keywords: histdata_downloader
Platform: UNKNOWN
Classifier: Development Status :: 2 - Pre-Alpha
Classifier: Intended Audience :: Developers
Classifier: License :: OSI Approved :: MIT License
Classifier: Natural Language :: English
Classifier: Programming Language :: Python :: 3
Classifier: Programming Language :: Python :: 3.5
Classifier: Programming Language :: Python :: 3.6
Classifier: Programming Language :: Python :: 3.7
Requires-Dist: Click (>=6.0)
Requires-Dist: beautifulsoup4
Requires-Dist: future-fstrings
Requires-Dist: lxml
Requires-Dist: pyaml
Requires-Dist: pandas
Requires-Dist: requests
Requires-Dist: tables
Requires-Dist: tqdm
Requires-Dist: h5py
